topsis/__init__.py
topsis/topsis.py
Topsis_Manav_102217159-1.0.0.dist-info/LICENSE
Topsis_Manav_102217159-1.0.0.dist-info/METADATA
Topsis_Manav_102217159-1.0.0.dist-info/WHEEL
Topsis_Manav_102217159-1.0.0.dist-info/entry_points.txt
Topsis_Manav_102217159-1.0.0.dist-info/top_level.txt
Topsis_Manav_102217159-1.0.0.dist-info/RECORD
